<ISNTD id="ISNTD" instanceID="uuid:9bbb263d-61a6-4d4b-b2c1-94402118fdb9" submissionDate="2018-03-27T16:01:38.000+01" isComplete="true" markedAsCompleteDate="2018-03-27T16:01:38.000+01" xmlns="http://opendatakit.org/submissions"><intro /><first_name>Bob Cheke</first_name><date_of_birth>1990-07-14</date_of_birth><post_started>1997-01-01</post_started><location_birth>51.5259877000 -0.1336914000 70.5000000000 13.9790000000</location_birth><fave_animal>cats</fave_animal><select_one_likert>3</select_one_likert><ed_vs_chrissy>Chrissy</ed_vs_chrissy><my_signature>1522162862068.jpg</my_signature><selfie>1522162880002.jpg</selfie><n0:meta xmlns:n0="http://openrosa.org/xforms"><n0:instanceID>uuid:9bbb263d-61a6-4d4b-b2c1-94402118fdb9</n0:instanceID></n0:meta></ISNTD>